aiovkcom/__init__.py
aiovkcom/api.py
aiovkcom/session.py
aiovkcom-1.0.0.dist-info/LICENSE
aiovkcom-1.0.0.dist-info/METADATA
aiovkcom-1.0.0.dist-info/WHEEL
aiovkcom-1.0.0.dist-info/top_level.txt
aiovkcom-1.0.0.dist-info/RECORD
