Metadata-Version: 2.1
Name: aiovkcom
Version: 1.0.0
Summary: Python vk.com API wrapper
Home-page: https://github.com/konstantintogoi/aiovkcom
Download-URL: https://pypi.org/project/aiovkcom/
Author: Konstantin Togoi
Author-email: Konstantin Togoi <konstantin.togoi@gmail.com>
License: BSD 2-Clause License
Project-URL: Home, https://pypi.org/project/aiovkcom
Project-URL: Documentation, https://konstantintogoi.github.io/aiovkcom
Project-URL: Repository, https://github.com/konstantintogoi/aiovkcom
Keywords: vk,vk api
Platform: Any
Classifier: Development Status :: 5 - Production/Stable
Classifier: Environment :: Web Environment
Classifier: Framework :: AsyncIO
Classifier: Intended Audience :: Developers
Classifier: License :: OSI Approved :: BSD License
Classifier: Operating System :: OS Independent
Classifier: Programming Language :: Python
Classifier: Programming Language :: Python :: 3.7
Classifier: Programming Language :: Python :: 3.8
Classifier: Programming Language :: Python :: 3.9
Classifier: Programming Language :: Python :: 3 :: Only
Classifier: Topic :: Internet
Classifier: Topic :: Internet :: WWW/HTTP
Classifier: Topic :: Software Development :: Libraries :: Python Modules
Requires-Python: >=3.7
License-File: LICENSE
Requires-Dist: httpx
